gdscene/__init__.py
gdscene/__main__.py
gdscene-0.0.1.dist-info/DESCRIPTION.rst
gdscene-0.0.1.dist-info/METADATA
gdscene-0.0.1.dist-info/RECORD
gdscene-0.0.1.dist-info/WHEEL
gdscene-0.0.1.dist-info/entry_points.txt
gdscene-0.0.1.dist-info/metadata.json
gdscene-0.0.1.dist-info/top_level.txt
